{"networkName": "Model 32", "networkID": 207, "networkMeta": {"openStatistics": null, "openTest": null, "zoom": 1, "zoomSnapshot": 1, "netMode": "edit", "coreStatus": {"Status": "Waiting"}, "chartsRequest": {"timerID": null, "waitGlobalEvent": false, "doRequest": 0, "showCharts": 0}}, "networkElementList": {}, "networkRootFolder": "C:\\Users\\Robert\\Documents\\Perceptilabs\\Default/Model 32", "apiMeta": {"model_id": 180, "project": 5, "name": "GAN 3", "created": "2020-09-04T09:11:33.839150Z", "updated": "2020-09-04T09:11:33.839150Z", "saved_by": "", "location": "C:\\Users\\Robert\\Documents\\Perceptilabs\\Default/GAN 3", "saved_version_location": ""}}